cryptography/__init__.py
cryptography/alphabet.py
cryptography/caesar.py
cryptography_lib-0.1.0.dist-info/METADATA
cryptography_lib-0.1.0.dist-info/WHEEL
cryptography_lib-0.1.0.dist-info/top_level.txt
cryptography_lib-0.1.0.dist-info/RECORD
